scieloh5m5
tests
