Metadata-Version: 1.1
Name: scieloh5m5
Version: 1.5.4
Summary: Library to delivery H5 M5 Google Scholar metrics for the SciELO Journals
Home-page: http://github.com/scieloorg/processing
Author: Fabio Batalha
Author-email: fabio.batalha@scielo.org
License: UNKNOWN
Platform: UNKNOWN
Classifier: Development Status :: 4 - Beta
Classifier: Intended Audience :: Developers
Classifier: Programming Language :: Python :: 3
Classifier: Programming Language :: Python :: 2.7
